sqlalchemy_toolbox/__init__.py
sqlalchemy_toolbox/base_model.py
sqlalchemy_toolbox/configuration.py
sqlalchemy_toolbox/constants.py
sqlalchemy_toolbox/database_type.py
sqlalchemy_toolbox/exceptions.py
sqlalchemy_toolbox/migrations.py
sqlalchemy_toolbox/utils/__init__.py
sqlalchemy_toolbox/utils/version.py
sqlalchemy_toolbox/wrappers/__init__.py
sqlalchemy_toolbox/wrappers/wrapper.py
sqlalchemy_toolbox-0.1.2.dist-info/LICENSE
sqlalchemy_toolbox-0.1.2.dist-info/METADATA
sqlalchemy_toolbox-0.1.2.dist-info/WHEEL
sqlalchemy_toolbox-0.1.2.dist-info/top_level.txt
sqlalchemy_toolbox-0.1.2.dist-info/RECORD
