Metadata-Version: 2.1
Name: sqlalchemy-toolbox
Version: 0.1.2
Summary: A collection of sqlalchemy utility classes and functionalities that help in using sqlalchemy
Home-page: https://github.com/coding-kitties/sqlalchemy-toolbox.git
Author: coding kitties
Author-email: codingkitties@gmail.com
License: MIT
Keywords: SQLALCHEMY,SQL,ORM,DATABASE,ALEMBIC
Platform: UNKNOWN
Classifier: Intended Audience :: Developers
Classifier: Programming Language :: Python :: 3
Classifier: Programming Language :: Python :: 3.4
Classifier: Programming Language :: Python :: 3.5
Classifier: Programming Language :: Python :: 3.6
Classifier: Topic :: Software Development
Classifier: License :: OSI Approved :: MIT License
Requires-Python: >=3.6
Requires-Dist: wrapt (==1.11.2)
Requires-Dist: SQLAlchemy (==1.3.13)
Requires-Dist: Flask (==1.1.1)
Requires-Dist: setuptools (~=51.0.0)
Requires-Dist: configobj (~=5.0.6)
Requires-Dist: alembic (==1.5.2)
